tgzr/shell_services/settings/__init__.py
tgzr/shell_services/settings/_version.py
tgzr_shell_services_settings-0.100.dist-info/METADATA
tgzr_shell_services_settings-0.100.dist-info/WHEEL
tgzr_shell_services_settings-0.100.dist-info/entry_points.txt
tgzr_shell_services_settings-0.100.dist-info/licenses/LICENSE
tgzr_shell_services_settings-0.100.dist-info/RECORD
